<?xml version="1.0" encoding="utf-8"?> <?xml-stylesheet type="text/xsl" href="Dish.xslt"?> <Dish id="1"       xmlns="http://dishShop/Dish"       xmlns:xsi="http://www.w3.org/2001/XMLSchema-instance"       xsi:schemaLocation="http://dishShop/Dish Dish.xsd"       xmlns:mat="http://dishShop/Material"       xmlns:col="http://dishShop/Color"       xmlns:cat="http://dishShop/Category"> 	<Name>NewDish</Name> 	<Volume>200</Volume> 	<Price>10.99</Price> 	<Material id="1"> 		<mat:Name>Wood</mat:Name> 	</Material> 	<Color id="1"> 		<col:HexValue>#964B00</col:HexValue> 		<col:Name>Brown</col:Name> 	</Color> 	<Categories> 		<cat:Category id="1"> 			<cat:Name>Wooden</cat:Name> 		</cat:Category> 		<cat:Category id="2"> 			<cat:Name>Forks</cat:Name> 		</cat:Category> 	</Categories> </Dish>